m2data/__init__.py
m2data/correction.py
m2data/example.py
m2data/reader.py
m2data/token_alignments.py
tests/__init__.py
tests/correction.py
tests/example.py
tests/reader.py
m2data-0.0.14.dist-info/LICENSE
m2data-0.0.14.dist-info/METADATA
m2data-0.0.14.dist-info/WHEEL
m2data-0.0.14.dist-info/top_level.txt
m2data-0.0.14.dist-info/RECORD
