Metadata-Version: 2.1
Name: m2data
Version: 0.0.14
Summary: A package for reading .m2 files commonly used in GEC tasks
Home-page: https://github.com/Mindful/m2data
Author: Joshua Tanner
Author-email: mindful.jt@gmail.com
License: UNKNOWN
Keywords: grammatical error correction,GEC,natural langauge processing
Platform: UNKNOWN
Classifier: Programming Language :: Python :: 3
Classifier: License :: OSI Approved :: MIT License
Classifier: Operating System :: OS Independent
Requires-Python: >=3.6
License-File: LICENSE
